[
  {
    "id": "映画 この素晴らしい世界に祝福を！紅伝説",
    "title": "映画 この素晴らしい世界に祝福を！紅伝説",
    "url": "https://video.unext.jp/title/SID0055027"
  },
  {
    "id": "この素晴らしい世界に祝福を！",
    "title": "この素晴らしい世界に祝福を！",
    "url": "https://video.unext.jp/title/SID0021369"
  },
  {
    "id": "この素晴らしい世界に祝福を！２",
    "title": "この素晴らしい世界に祝福を！２",
    "url": "https://video.unext.jp/title/SID0027978"
  },
  {
    "id": "この素晴らしい世界に祝福を！３",
    "title": "この素晴らしい世界に祝福を！３",
    "url": "https://video.unext.jp/title/SID0100051"
  },
  {
    "id": "この素晴らしい世界に爆焔を！",
    "title": "この素晴らしい世界に爆焔を！",
    "url": "https://video.unext.jp/title/SID0079684"
  },
  {
    "id": "この世界の片隅に",
    "title": "この世界の片隅に",
    "url": "https://video.unext.jp/title/SID0029241"
  },
  {
    "id": "この世界の（さらにいくつもの）片隅に",
    "title": "この世界の（さらにいくつもの）片隅に",
    "url": "https://video.unext.jp/title/SID0050421"
  },
  {
    "id": "この世界は不完全すぎる",
    "title": "この世界は不完全すぎる",
    "url": "https://video.unext.jp/title/SID0157563"
  },
  {
    "id": "この男子、宇宙人と戦えます。",
    "title": "この男子、宇宙人と戦えます。",
    "url": "https://video.unext.jp/title/SID0013574"
  },
  {
    "id": "この男子、石化に悩んでます。",
    "title": "この男子、石化に悩んでます。",
    "url": "https://video.unext.jp/title/SID0013614"
  },
  {
    "id": "この男子、人魚ひろいました。",
    "title": "この男子、人魚ひろいました。",
    "url": "https://video.unext.jp/title/SID0013575"
  },
  {
    "id": "この男子、魔法がお仕事です。",
    "title": "この男子、魔法がお仕事です。",
    "url": "https://video.unext.jp/title/SID0022250"
  },
  {
    "id": "この中に１人、妹がいる！",
    "title": "この中に１人、妹がいる！",
    "url": "https://video.unext.jp/title/SID0017669"
  },
  {
    "id": "このはな綺譚",
    "title": "このはな綺譚",
    "url": "https://video.unext.jp/title/SID0031287"
  },
  {
    "id": "このヒーラー、めんどくさい",
    "title": "このヒーラー、めんどくさい",
    "url": "https://video.unext.jp/title/SID0066879"
  },
  {
    "id": "この美術部には問題がある！",
    "title": "この美術部には問題がある！",
    "url": "https://video.unext.jp/title/SID0025878"
  },
  {
    "id": "この醜くも美しい世界",
    "title": "この醜くも美しい世界",
    "url": "https://video.unext.jp/title/SID0014844"
  },
  {
    "id": "この世の果てで恋を唄う少女YU-NO",
    "title": "この世の果てで恋を唄う少女YU-NO",
    "url": "https://video.unext.jp/title/SID0040644"
  },
  {
    "id": "こばと。",
    "title": "こばと。",
    "url": "https://video.unext.jp/title/SID0034756"
  },
  {
    "id": "小林さんちのメイドラゴン",
    "title": "小林さんちのメイドラゴン",
    "url": "https://video.unext.jp/title/SID0027929"
  },
  {
    "id": "小林さんちのメイドラゴンS",
    "title": "小林さんちのメイドラゴンS",
    "url": "https://video.unext.jp/title/SID0058496"
  },
  {
    "id": "こひつじのティミー",
    "title": "こひつじのティミー",
    "url": "https://video.unext.jp/title/SID0017791"
  },
  {
    "id": "こびとす",
    "title": "こびとす",
    "url": "https://video.unext.jp/title/SID0031366"
  },
  {
    "id": "こぴはん",
    "title": "こぴはん",
    "url": "https://video.unext.jp/title/SID0003312"
  },
  {
    "id": "古墳ギャルのコフィー",
    "title": "古墳ギャルのコフィー",
    "url": "https://video.unext.jp/title/SID0003210"
  },
  {
    "id": "COBRA THE ANIMATION タイム・ドライブ",
    "title": "COBRA THE ANIMATION タイム・ドライブ",
    "url": "https://video.unext.jp/title/SID0014861"
  },
  {
    "id": "COBRA THE ANIMATION ザ・サイコガン",
    "title": "COBRA THE ANIMATION ザ・サイコガン",
    "url": "https://video.unext.jp/title/SID0014860"
  },
  {
    "id": "COBRA THE ANIMATION",
    "title": "COBRA THE ANIMATION",
    "url": "https://video.unext.jp/title/SID0014859"
  },
  {
    "id": "コボちゃん（TVシリーズ）",
    "title": "コボちゃん（TVシリーズ）",
    "url": "https://video.unext.jp/title/SID0018483"
  },
  {
    "id": "コボちゃんスペシャル 約束のマジックデイ",
    "title": "コボちゃんスペシャル 約束のマジックデイ",
    "url": "https://video.unext.jp/title/SID0012624"
  },
  {
    "id": "コボちゃんスペシャル 祭りがいっぱい！",
    "title": "コボちゃんスペシャル 祭りがいっぱい！",
    "url": "https://video.unext.jp/title/SID0012623"
  },
  {
    "id": "コボちゃんスペシャル 夢いっぱい!!",
    "title": "コボちゃんスペシャル 夢いっぱい!!",
    "url": "https://video.unext.jp/title/SID0012622"
  },
  {
    "id": "コボちゃんスペシャル 秋がいっぱい!!",
    "title": "コボちゃんスペシャル 秋がいっぱい!!",
    "url": "https://video.unext.jp/title/SID0012621"
  },
  {
    "id": "駒田蒸留所へようこそ",
    "title": "駒田蒸留所へようこそ",
    "url": "https://video.unext.jp/title/SID0148674"
  },
  {
    "id": "こま撮りえいが こまねこ",
    "title": "こま撮りえいが こまねこ",
    "url": "https://video.unext.jp/title/SID0003391"
  },
  {
    "id": "こまねこのクリスマス 迷子になったプレゼント",
    "title": "こまねこのクリスマス 迷子になったプレゼント",
    "url": "https://video.unext.jp/title/SID0003392"
  },
  {
    "id": "こみっくがーるず",
    "title": "こみっくがーるず",
    "url": "https://video.unext.jp/title/SID0034193"
  },
  {
    "id": "小森さんは断れない！",
    "title": "小森さんは断れない！",
    "url": "https://video.unext.jp/title/SID0042775"
  },
  {
    "id": "今宵、アフレコブースで。",
    "title": "今宵、アフレコブースで。",
    "url": "https://video.unext.jp/title/SID0042195"
  },
  {
    "id": "暦物語",
    "title": "暦物語",
    "url": "https://video.unext.jp/title/SID0037810"
  },
  {
    "id": "コヨーテラグタイムショー",
    "title": "コヨーテラグタイムショー",
    "url": "https://video.unext.jp/title/SID0014868"
  },
  {
    "id": "コルボッコロ",
    "title": "コルボッコロ",
    "url": "https://video.unext.jp/title/SID0056468"
  },
  {
    "id": "これがＵＦＯだ！空飛ぶ円盤",
    "title": "これがＵＦＯだ！空飛ぶ円盤",
    "url": "https://video.unext.jp/title/SID0091510"
  },
  {
    "id": "コレクター・ユイ　デジタル・リマスター版　第１シリーズ",
    "title": "コレクター・ユイ　デジタル・リマスター版　第１シリーズ",
    "url": "https://video.unext.jp/title/SID0162519"
  },
  {
    "id": "コレクター・ユイ　デジタル・リマスター版　第２シリーズ",
    "title": "コレクター・ユイ　デジタル・リマスター版　第２シリーズ",
    "url": "https://video.unext.jp/title/SID0162520"
  },
  {
    "id": "これはゾンビですか？",
    "title": "これはゾンビですか？",
    "url": "https://video.unext.jp/title/SID0035435"
  },
  {
    "id": "これはゾンビですか？オブ・ザ・デッド",
    "title": "これはゾンビですか？オブ・ザ・デッド",
    "url": "https://video.unext.jp/title/SID0035436"
  },
  {
    "id": "コロコロアニマル",
    "title": "コロコロアニマル",
    "url": "https://video.unext.jp/title/SID0002209"
  },
  {
    "id": "殺し愛",
    "title": "殺し愛",
    "url": "https://video.unext.jp/title/SID0063374"
  },
  {
    "id": "殺せんせーQ！",
    "title": "殺せんせーQ！",
    "url": "https://video.unext.jp/title/SID0027529"
  },
  {
    "id": "こわぼん",
    "title": "こわぼん",
    "url": "https://video.unext.jp/title/SID0020197"
  },
  {
    "id": "金色のガッシュベル!!",
    "title": "金色のガッシュベル!!",
    "url": "https://video.unext.jp/title/SID0011165"
  },
  {
    "id": "CONCEPTION－コンセプション",
    "title": "CONCEPTION－コンセプション",
    "url": "https://video.unext.jp/title/SID0037223"
  },
  {
    "id": "昆虫物語みなしごハッチ",
    "title": "昆虫物語みなしごハッチ",
    "url": "https://video.unext.jp/title/SID0017887"
  },
  {
    "id": "昆虫物語 新みなしごハッチ",
    "title": "昆虫物語 新みなしごハッチ",
    "url": "https://video.unext.jp/title/SID0017888"
  },
  {
    "id": "こんにちはアン",
    "title": "こんにちはアン",
    "url": "https://video.unext.jp/title/SID0002210"
  },
  {
    "id": "#コンパス2.0 戦闘摂理解析システム ANIMATION PROJECT",
    "title": "#コンパス2.0 戦闘摂理解析システム ANIMATION PROJECT",
    "url": "https://video.unext.jp/title/SID0181243"
  },
  {
    "id": "コンビニカレシ",
    "title": "コンビニカレシ",
    "url": "https://video.unext.jp/title/SID0030144"
  },
  {
    "id": "紺碧の艦隊",
    "title": "紺碧の艦隊",
    "url": "https://video.unext.jp/title/SID0002602"
  },
  {
    "id": "婚約破棄された令嬢を拾った俺が、イケナイことを教え込む",
    "title": "婚約破棄された令嬢を拾った俺が、イケナイことを教え込む",
    "url": "https://video.unext.jp/title/SID0091711"
  },
  {
    "id": "コードギアス 反逆のルルーシュ I 興道",
    "title": "コードギアス 反逆のルルーシュ I 興道",
    "url": "https://video.unext.jp/title/SID0033205"
  },
  {
    "id": "コードギアス 反逆のルルーシュII 叛道",
    "title": "コードギアス 反逆のルルーシュII 叛道",
    "url": "https://video.unext.jp/title/SID0035259"
  },
  {
    "id": "コードギアス 反逆のルルーシュ III 皇道",
    "title": "コードギアス 反逆のルルーシュ III 皇道",
    "url": "https://video.unext.jp/title/SID0037120"
  },
  {
    "id": "コードギアス 反逆のルルーシュ SPECIAL EDITION ‘BLACK REBELLION’",
    "title": "コードギアス 反逆のルルーシュ SPECIAL EDITION ‘BLACK REBELLION’",
    "url": "https://video.unext.jp/title/SID0014799"
  },
  {
    "id": "コードギアス 反逆のルルーシュ キセキの誕生日（バースデー）",
    "title": "コードギアス 反逆のルルーシュ キセキの誕生日（バースデー）",
    "url": "https://video.unext.jp/title/SID0014798"
  },
  {
    "id": "コードギアス 反逆のルルーシュ",
    "title": "コードギアス 反逆のルルーシュ",
    "url": "https://video.unext.jp/title/SID0002580"
  },
  {
    "id": "コードギアス 反逆のルルーシュ R2 SPECIAL EDITION ‘ZERO REQUIEM’",
    "title": "コードギアス 反逆のルルーシュ R2 SPECIAL EDITION ‘ZERO REQUIEM’",
    "url": "https://video.unext.jp/title/SID0014797"
  },
  {
    "id": "コードギアス 反逆のルルーシュ R2",
    "title": "コードギアス 反逆のルルーシュ R2",
    "url": "https://video.unext.jp/title/SID0013601"
  },
  {
    "id": "コードギアス 復活のルルーシュ",
    "title": "コードギアス 復活のルルーシュ",
    "url": "https://video.unext.jp/title/SID0044110"
  },
  {
    "id": "コードギアス 亡国のアキト",
    "title": "コードギアス 亡国のアキト",
    "url": "https://video.unext.jp/title/SID0013602"
  },
  {
    "id": "CORUSCATE -DNA-",
    "title": "CORUSCATE -DNA-",
    "url": "https://video.unext.jp/title/SID0070436"
  },
  {
    "id": "Call Star-ボクは本当にダメな星？-",
    "title": "Call Star-ボクは本当にダメな星？-",
    "url": "https://video.unext.jp/title/SID0076934"
  },
  {
    "id": "合コンに行ったら女がいなかった話",
    "title": "合コンに行ったら女がいなかった話",
    "url": "https://video.unext.jp/title/SID0157064"
  },
  {
    "id": "5億年ボタン【公式】～菅原そうたのショートショート",
    "title": "5億年ボタン【公式】～菅原そうたのショートショート",
    "url": "https://video.unext.jp/title/SID0070107"
  },
  {
    "id": "ご姉弟物語",
    "title": "ご姉弟物語",
    "url": "https://video.unext.jp/title/SID0044383"
  },
  {
    "id": "ご近所物語",
    "title": "ご近所物語",
    "url": "https://video.unext.jp/title/SID0014812"
  },
  {
    "id": "悟空の大冒険",
    "title": "悟空の大冒険",
    "url": "https://video.unext.jp/title/SID0002207"
  },
  {
    "id": "極黒のブリュンヒルデ",
    "title": "極黒のブリュンヒルデ",
    "url": "https://video.unext.jp/title/SID0002584"
  },
  {
    "id": "【獄・】さよなら絶望先生",
    "title": "【獄・】さよなら絶望先生",
    "url": "https://video.unext.jp/title/SID0063587"
  },
  {
    "id": "極上!!めちゃモテ委員長",
    "title": "極上!!めちゃモテ委員長",
    "url": "https://video.unext.jp/title/SID0063390"
  },
  {
    "id": "GOSICK-ゴシック-",
    "title": "GOSICK-ゴシック-",
    "url": "https://video.unext.jp/title/SID0012994"
  },
  {
    "id": "ご愁傷さま二ノ宮くん",
    "title": "ご愁傷さま二ノ宮くん",
    "url": "https://video.unext.jp/title/SID0042778"
  },
  {
    "id": "GODZILLA 怪獣惑星",
    "title": "GODZILLA 怪獣惑星",
    "url": "https://video.unext.jp/title/SID0040735"
  },
  {
    "id": "GODZILLA 決戦機動増殖都市",
    "title": "GODZILLA 決戦機動増殖都市",
    "url": "https://video.unext.jp/title/SID0044830"
  },
  {
    "id": "GODZILLA 星を喰う者",
    "title": "GODZILLA 星を喰う者",
    "url": "https://video.unext.jp/title/SID0044951"
  },
  {
    "id": "ごぞんじ！月光仮面くん",
    "title": "ごぞんじ！月光仮面くん",
    "url": "https://video.unext.jp/title/SID0038234"
  },
  {
    "id": "ご注文はうさぎですか？",
    "title": "ご注文はうさぎですか？",
    "url": "https://video.unext.jp/title/SID0012723"
  },
  {
    "id": "ご注文はうさぎですか？？",
    "title": "ご注文はうさぎですか？？",
    "url": "https://video.unext.jp/title/SID0019865"
  },
  {
    "id": "ご注文はうさぎですか？？ ～Dear My Sister～",
    "title": "ご注文はうさぎですか？？ ～Dear My Sister～",
    "url": "https://video.unext.jp/title/SID0035615"
  },
  {
    "id": "ご注文はうさぎですか？？ ～Sing For You～",
    "title": "ご注文はうさぎですか？？ ～Sing For You～",
    "url": "https://video.unext.jp/title/SID0044959"
  },
  {
    "id": "ご注文はうさぎですか？ BLOOM",
    "title": "ご注文はうさぎですか？ BLOOM",
    "url": "https://video.unext.jp/title/SID0050914"
  },
  {
    "id": "THE GOD OF HIGH SCHOOL ゴッド・オブ・ハイスクール",
    "title": "THE GOD OF HIGH SCHOOL ゴッド・オブ・ハイスクール",
    "url": "https://video.unext.jp/title/SID0049166"
  },
  {
    "id": "ゴッドマジンガー",
    "title": "ゴッドマジンガー",
    "url": "https://video.unext.jp/title/SID0039465"
  },
  {
    "id": "五等分の花嫁＊",
    "title": "五等分の花嫁＊",
    "url": "https://video.unext.jp/title/SID0166684"
  },
  {
    "id": "五等分の花嫁スペシャルイベント",
    "title": "五等分の花嫁スペシャルイベント",
    "url": "https://video.unext.jp/title/SID0047970"
  },
  {
    "id": "五等分の花嫁∬ SPECIAL EVENT 2021 in 中野サンプラザ",
    "title": "五等分の花嫁∬ SPECIAL EVENT 2021 in 中野サンプラザ",
    "url": "https://video.unext.jp/title/SID0067502"
  },
  {
    "id": "五等分の花嫁",
    "title": "五等分の花嫁",
    "url": "https://video.unext.jp/title/SID0039101"
  },
  {
    "id": "五等分の花嫁∬",
    "title": "五等分の花嫁∬",
    "url": "https://video.unext.jp/title/SID0052903"
  },
  {
    "id": "五等分の花嫁∽",
    "title": "五等分の花嫁∽",
    "url": "https://video.unext.jp/title/SID0091852"
  },
  {
    "id": "ゴブリンスレイヤー",
    "title": "ゴブリンスレイヤー",
    "url": "https://video.unext.jp/title/SID0037156"
  },
  {
    "id": "ゴブリンスレイヤー -GOBLIN'S CROWN-",
    "title": "ゴブリンスレイヤー -GOBLIN'S CROWN-",
    "url": "https://video.unext.jp/title/SID0051713"
  },
  {
    "id": "ゴブリンスレイヤーII",
    "title": "ゴブリンスレイヤーII",
    "url": "https://video.unext.jp/title/SID0092057"
  },
  {
    "id": "ゴミおばけがやってきた",
    "title": "ゴミおばけがやってきた",
    "url": "https://video.unext.jp/title/SID0182931"
  },
  {
    "id": "ごめんね",
    "title": "ごめんね",
    "url": "https://video.unext.jp/title/SID0214848"
  },
  {
    "id": "ゴリラの神から加護された令嬢は王立騎士団で可愛がられる",
    "title": "ゴリラの神から加護された令嬢は王立騎士団で可愛がられる",
    "url": "https://video.unext.jp/title/SID0181250"
  },
  {
    "id": "ゴルゴ13（1971）",
    "title": "ゴルゴ13（1971）",
    "url": "https://video.unext.jp/title/SID0097089"
  },
  {
    "id": "ゴルゴ13",
    "title": "ゴルゴ13",
    "url": "https://video.unext.jp/title/SID0038635"
  },
  {
    "id": "ゴワッパー５ ゴーダム",
    "title": "ゴワッパー５ ゴーダム",
    "url": "https://video.unext.jp/title/SID0017857"
  },
  {
    "id": "GO!GO!アトム",
    "title": "GO!GO!アトム",
    "url": "https://video.unext.jp/title/SID0047340"
  },
  {
    "id": "GO!GO!TOKYO MER 緊急事態と戦う仲間達",
    "title": "GO!GO!TOKYO MER 緊急事態と戦う仲間達",
    "url": "https://video.unext.jp/title/SID0088708"
  },
  {
    "id": "ゴー！ゴー！びーくるずー",
    "title": "ゴー！ゴー！びーくるずー",
    "url": "https://video.unext.jp/title/SID0079944"
  },
  {
    "id": "ゴー！ゴー！びーくるずー のりものスター編",
    "title": "ゴー！ゴー！びーくるずー のりものスター編",
    "url": "https://video.unext.jp/title/SID0187466"
  },
  {
    "id": "ゴーゴー！マジムン",
    "title": "ゴーゴー！マジムン",
    "url": "https://video.unext.jp/title/SID0027740"
  },
  {
    "id": "GHOST IN THE SHELL 攻殻機動隊",
    "title": "GHOST IN THE SHELL 攻殻機動隊",
    "url": "https://video.unext.jp/title/SID0012986"
  },
  {
    "id": "GS美神",
    "title": "GS美神",
    "url": "https://video.unext.jp/title/SID0014785"
  },
  {
    "id": "520",
    "title": "520",
    "url": "https://video.unext.jp/title/SID0090655"
  },
  {
    "id": "Go！プリンセスプリキュア",
    "title": "Go！プリンセスプリキュア",
    "url": "https://video.unext.jp/title/SID0026002"
  },
  {
    "id": "ゴールデンカムイ OAD 第一弾",
    "title": "ゴールデンカムイ OAD 第一弾",
    "url": "https://video.unext.jp/title/SID0063520"
  },
  {
    "id": "ゴールデンカムイ OAD 第三弾",
    "title": "ゴールデンカムイ OAD 第三弾",
    "url": "https://video.unext.jp/title/SID0075199"
  },
  {
    "id": "ゴールデンカムイ OAD 第二弾",
    "title": "ゴールデンカムイ OAD 第二弾",
    "url": "https://video.unext.jp/title/SID0063521"
  },
  {
    "id": "ゴールデンカムイ　オーディオコメンタリー版",
    "title": "ゴールデンカムイ　オーディオコメンタリー版",
    "url": "https://video.unext.jp/title/SID0056347"
  },
  {
    "id": "ゴールデンカムイ",
    "title": "ゴールデンカムイ",
    "url": "https://video.unext.jp/title/SID0035986"
  },
  {
    "id": "ゴールデンカムイ　第二期　オーディオコメンタリー版",
    "title": "ゴールデンカムイ　第二期　オーディオコメンタリー版",
    "url": "https://video.unext.jp/title/SID0056348"
  },
  {
    "id": "ゴールデンカムイ　第二期",
    "title": "ゴールデンカムイ　第二期",
    "url": "https://video.unext.jp/title/SID0038894"
  },
  {
    "id": "ゴールデンカムイ　第三期",
    "title": "ゴールデンカムイ　第三期",
    "url": "https://video.unext.jp/title/SID0050922"
  },
  {
    "id": "ゴールデンカムイ　第四期",
    "title": "ゴールデンカムイ　第四期",
    "url": "https://video.unext.jp/title/SID0073131"
  },
  {
    "id": "ゴールデンタイム",
    "title": "ゴールデンタイム",
    "url": "https://video.unext.jp/title/SID0014807"
  },
  {
    "id": "GOLDEN BOY さすらいのお勉強野郎",
    "title": "GOLDEN BOY さすらいのお勉強野郎",
    "url": "https://video.unext.jp/title/SID0003209"
  },
  {
    "id": "ゴールライン (Argonavis 0-BEYOND LIVE -始動-)",
    "title": "ゴールライン (Argonavis 0-BEYOND LIVE -始動-)",
    "url": "https://video.unext.jp/title/SID0058477"
  },
  {
    "id": "ゴールライン (BanG Dream! Argonavis 1st LIVE)",
    "title": "ゴールライン (BanG Dream! Argonavis 1st LIVE)",
    "url": "https://video.unext.jp/title/SID0058478"
  }
]